personalnames/__init__.py
personalnames/names.py
personalnames/titles.py
personalnames-0.0.2.dist-info/METADATA
personalnames-0.0.2.dist-info/RECORD
personalnames-0.0.2.dist-info/WHEEL
personalnames-0.0.2.dist-info/top_level.txt
tests/__init__.py
tests/test_names.py
