Metadata-Version: 2.1
Name: personalnames
Version: 0.0.2
Summary: Generate variant forms for personal names.
Home-page: https://github.com/digirati-co-uk/personalnames
Author: Matt McGrattan
Author-email: matt.mcgrattan@digirati.com
License: UNKNOWN
Platform: UNKNOWN
Classifier: Programming Language :: Python :: 3
Classifier: License :: OSI Approved :: MIT License
Classifier: Operating System :: OS Independent
